arxiv_downloader/__init__.py
arxiv_downloader-1.0.0.data/scripts/arxiv-downloader
arxiv_downloader-1.0.0.dist-info/LICENSE
arxiv_downloader-1.0.0.dist-info/METADATA
arxiv_downloader-1.0.0.dist-info/WHEEL
arxiv_downloader-1.0.0.dist-info/top_level.txt
arxiv_downloader-1.0.0.dist-info/RECORD
