Metadata-Version: 2.1
Name: arxiv-downloader
Version: 1.0.0
Summary: A command line interface to download PDF files from https://arxiv.org.
Home-page: https://github.com/braun-steven/arxiv-downloader
Author: Steven Braun
Author-email: steven.braun.mz@gmail.com  
Project-URL: Bug Tracker, https://github.com/braun-steven/arxiv-downloader/issues
Classifier: Programming Language :: Python :: 3
Classifier: License :: OSI Approved :: MIT License
Classifier: Operating System :: OS Independent
Requires-Python: >=3.6
License-File: LICENSE
Requires-Dist: arxiv==2.1.0
